LICENSE
MANIFEST.in
README.txt
pyproject.toml
setup.py
OASYS2_XOPPY.egg-info/PKG-INFO
OASYS2_XOPPY.egg-info/SOURCES.txt
OASYS2_XOPPY.egg-info/dependency_links.txt
OASYS2_XOPPY.egg-info/entry_points.txt
OASYS2_XOPPY.egg-info/not-zip-safe
OASYS2_XOPPY.egg-info/requires.txt
OASYS2_XOPPY.egg-info/top_level.txt
orangecontrib/__init__.py
orangecontrib/xoppy/__init__.py
orangecontrib/xoppy/menu/__init__.py
orangecontrib/xoppy/menu/xoppy_tools_menu.py
orangecontrib/xoppy/util/__init__.py
orangecontrib/xoppy/util/python_script.py
orangecontrib/xoppy/util/xoppy_pymca_tools.py
orangecontrib/xoppy/util/script/__init__.py
orangecontrib/xoppy/util/script/itemmodels.py
orangecontrib/xoppy/util/script/python_script.py
orangecontrib/xoppy/util/script/variable.py
orangecontrib/xoppy/widgets/__init__.py
orangecontrib/xoppy/widgets/gui/__init__.py
orangecontrib/xoppy/widgets/gui/image_view_with_fwhm.py
orangecontrib/xoppy/widgets/gui/messages.py
orangecontrib/xoppy/widgets/gui/ow_xoppy_widget.py
orangecontrib/xoppy/widgets/gui/ow_xoppy_widget_dabax.py
orangecontrib/xoppy/widgets/gui/text_window.py
orangecontrib/xoppy/widgets/gui/xoppy_util.py
orangecontrib/xoppy/widgets/optics/__init__.py
orangecontrib/xoppy/widgets/optics/mare.py
orangecontrib/xoppy/widgets/optics/multilayer.py
orangecontrib/xoppy/widgets/optics/power1Dmonochromator.py
orangecontrib/xoppy/widgets/optics/power3Dcomponent.py
orangecontrib/xoppy/widgets/optics/srcalc_idpower.py
orangecontrib/xoppy/widgets/optics/xcrosssec.py
orangecontrib/xoppy/widgets/optics/xcrystal.py
orangecontrib/xoppy/widgets/optics/xf0.py
orangecontrib/xoppy/widgets/optics/xf1f2.py
orangecontrib/xoppy/widgets/optics/xfh.py
orangecontrib/xoppy/widgets/optics/xinpro.py
orangecontrib/xoppy/widgets/optics/xpower.py
orangecontrib/xoppy/widgets/optics/xxcom.py
orangecontrib/xoppy/widgets/optics/icons/power1d_monochromator.png
orangecontrib/xoppy/widgets/optics/icons/srcalc.png
orangecontrib/xoppy/widgets/optics/icons/xoppy_2.png
orangecontrib/xoppy/widgets/optics/icons/xoppy_mare.png
orangecontrib/xoppy/widgets/optics/icons/xoppy_mlayer.png
orangecontrib/xoppy/widgets/optics/icons/xoppy_power3d.png
orangecontrib/xoppy/widgets/optics/icons/xoppy_xcrosssec.png
