Metadata-Version: 2.4
Name: OASYS2-XOPPY
Version: 1.0.12
Summary: XOPPY: XOP (X-ray oriented programs) in Python
Home-page: https://github.com/oasys-kit/XOPPY
Download-URL: https://github.com/oasys-kit/XOPPY
Author: Manuel Sanchez del Rio, Luca Rebuffi, and Bioinformatics Laboratory, FRI UL
Author-email: srio@esrf.eu, lrebuffi@anl.gov
License: GPLv3
Keywords: X-ray optics,simulator,oasys2
Classifier: Development Status :: 5 - Production/Stable
Classifier: Environment :: X11 Applications :: Qt
Classifier: Environment :: Console
Classifier: Environment :: Plugins
Classifier: Programming Language :: Python :: 3
Classifier: Intended Audience :: Science/Research
License-File: LICENSE
Requires-Dist: oasys2>=0.0.39
Requires-Dist: xoppylib>=1.0.53
Dynamic: author
Dynamic: author-email
Dynamic: classifier
Dynamic: description
Dynamic: download-url
Dynamic: home-page
Dynamic: keywords
Dynamic: license
Dynamic: license-file
Dynamic: requires-dist
Dynamic: summary
